xarray_keras/__init__.py
xarray_keras/xrkeras.py
xarray_keras-0.11.dist-info/METADATA
xarray_keras-0.11.dist-info/WHEEL
xarray_keras-0.11.dist-info/top_level.txt
xarray_keras-0.11.dist-info/RECORD
