Metadata-Version: 2.1
Name: xarray-keras
Version: 0.11
Summary: xarray integration with keras
Home-page: https://github.com/user/reponame
Author: meteoia-team
Author-email: meteoai.consult@gmail.com
License: MIT
Download-URL: https://github.com/meteoia-team/xarray-keras/archive/0.1.zip
Keywords: xarray,keras,multidimension,deep learning
Platform: UNKNOWN
Classifier: Development Status :: 3 - Alpha
Classifier: Intended Audience :: Developers
Classifier: Topic :: Software Development :: Build Tools
Classifier: License :: OSI Approved :: MIT License
Classifier: Programming Language :: Python :: 3
Classifier: Programming Language :: Python :: 3.4
Classifier: Programming Language :: Python :: 3.5
Classifier: Programming Language :: Python :: 3.6
Requires-Dist: xarray
Requires-Dist: numpy
Requires-Dist: pandas
Requires-Dist: keras
Requires-Dist: sklearn
